dirB/__init__.py
dirB/base.py
dirB/merge.py
dirB/utils.py
dirB-0.2.3.dist-info/LICENSE
dirB-0.2.3.dist-info/METADATA
dirB-0.2.3.dist-info/WHEEL
dirB-0.2.3.dist-info/top_level.txt
dirB-0.2.3.dist-info/RECORD
