Metadata-Version: 2.1
Name: dirB
Version: 0.2.3
Summary: An I/O HDF5-based utility to assist in the distribution, execution and integration of data coming from different sources (e.g. results of mathematical optimization models).
Author-email: Santiago Fernández Prieto <mail.santiagofernandezprieto@gmail.com>, German Navarro <ge.najim@gmail.com>
License: Apache License
Project-URL: Homepage, https://github.com/bsc-quantic/dirB
Classifier: Programming Language :: Python :: 3
Classifier: Operating System :: OS Independent
Classifier: Topic :: System :: Archiving :: Mirroring
Requires-Python: >=3.10.7
License-File: LICENSE
Requires-Dist: h5py ==3.9.0
Requires-Dist: pandas ==2.0.2
